easydbconn/__init__.py
easydbconn/connections.py
easydbconn-0.1.3.dist-info/METADATA
easydbconn-0.1.3.dist-info/WHEEL
easydbconn-0.1.3.dist-info/top_level.txt
easydbconn-0.1.3.dist-info/RECORD
